alembic_converger/__init__.py
alembic_converger/cli.py
alembic_converger/config.py
alembic_converger/converge.py
alembic_converger/errors.py
alembic_converger/graph.py
alembic_converger/merge.py
alembic_converger/utils.py
alembic_converger/validate.py
alembic_converger-0.1.4.dist-info/licenses/LICENSE
alembic_converger-0.1.4.dist-info/METADATA
alembic_converger-0.1.4.dist-info/WHEEL
alembic_converger-0.1.4.dist-info/entry_points.txt
alembic_converger-0.1.4.dist-info/top_level.txt
alembic_converger-0.1.4.dist-info/RECORD
