Metadata-Version: 2.4
Name: alembic-converger
Version: 0.1.4
Summary: Safely converge Alembic migration graphs by generating minimal merge migrations
Author: Alembic Converger Contributors
License: MIT
Project-URL: Homepage, https://github.com/rishav00a/alembic_converger
Project-URL: Documentation, https://alembic-converger.readthedocs.io/en/latest/README.html
Project-URL: Issues, https://github.com/rishav00a/alembic_converger/issues
Project-URL: Repository, https://github.com/rishav00a/alembic_converger
Keywords: alembic,migrations,database,merge,convergence
Classifier: Development Status :: 4 - Beta
Classifier: Intended Audience :: Developers
Classifier: License :: OSI Approved :: MIT License
Classifier: Operating System :: OS Independent
Classifier: Programming Language :: Python :: 3
Classifier: Programming Language :: Python :: 3.8
Classifier: Programming Language :: Python :: 3.9
Classifier: Programming Language :: Python :: 3.10
Classifier: Programming Language :: Python :: 3.11
Classifier: Programming Language :: Python :: 3.12
Classifier: Topic :: Database
Classifier: Topic :: Software Development :: Libraries :: Python Modules
Classifier: Topic :: Software Development :: Version Control
Requires-Python: >=3.8
License-File: LICENSE
Requires-Dist: alembic>=1.7.0
Requires-Dist: click>=8.0
Requires-Dist: colorama>=0.4.0
Provides-Extra: dev
Requires-Dist: pytest>=7.0; extra == "dev"
Requires-Dist: pytest-cov>=4.0; extra == "dev"
Requires-Dist: black>=23.0; extra == "dev"
Requires-Dist: ruff>=0.1.0; extra == "dev"
Dynamic: license-file
